mt/aio/__init__.py
mt/aio/base.py
mt/aio/files.py
mt/aio/multiprocessing.py
mt/aio/path.py
mt/aio/procedure.py
mt/asyncio/__init__.py
mt/base/__init__.py
mt/base/bg_invoke.py
mt/base/casting.py
mt/base/const.py
mt/base/contextlib.py
mt/base/datatype.py
mt/base/debug_process.py
mt/base/deprecated.py
mt/base/exec.py
mt/base/filetype.py
mt/base/functional.py
mt/base/hashing.py
mt/base/http.py
mt/base/locket.py
mt/base/model.py
mt/base/object_store.py
mt/base/path.py
mt/base/s3.py
mt/base/str.py
mt/base/terminal.py
mt/base/threading.py
mt/base/version.py
mt/base/zipfile.py
mt/concurrency/__init__.py
mt/concurrency/aio.py
mt/concurrency/base.py
mt/concurrency/beehive.py
mt/concurrency/multiprocessing.py
mt/ctx/__init__.py
mt/functools/__init__.py
mt/halo/__init__.py
mt/halo/halo.py
mt/halo/halo_notebook.py
mt/ipython/__init__.py
mt/ipython/ipython.py
mt/ipython/jupyter.py
mt/jax/__init__.py
mt/jnp/__init__.py
mt/jsp/__init__.py
mt/logg/__init__.py
mt/mpl/__init__.py
mt/np/__init__.py
mt/np/class_color.py
mt/np/image.py
mt/np/matrix.py
mt/np/ndarray.py
mt/np/sparse.py
mt/path/__init__.py
mt/plt/__init__.py
mt/shutil/__init__.py
mt/threading/__init__.py
mt/time/__init__.py
mt/tp/__init__.py
mt/traceback/__init__.py
mt/v4l2/__init__.py
mtbase-4.33.15.data/scripts/path_exists
mtbase-4.33.15.dist-info/licenses/LICENSE
mtbase-4.33.15.dist-info/METADATA
mtbase-4.33.15.dist-info/WHEEL
mtbase-4.33.15.dist-info/top_level.txt
mtbase-4.33.15.dist-info/RECORD
