Metadata-Version: 2.4
Name: mtbase
Version: 4.33.15
Summary: The most fundamental Python modules for Minh-Tri Pham
Home-page: https://github.com/inteplus/mtbase
Author: ['Minh-Tri Pham']
License: MIT
Project-URL: Documentation, https://mtdoc.readthedocs.io/en/latest/mt.base/mt.base.html
Project-URL: Source Code, https://github.com/inteplus/mtbase
Requires-Python: >=3.6
License-File: LICENSE
Requires-Dist: mtuv
Requires-Dist: psutil
Requires-Dist: colorama
Requires-Dist: numpy
Requires-Dist: aiofiles
Requires-Dist: aioshutil
Requires-Dist: aiohttp
Requires-Dist: aioboto3
Requires-Dist: filetype
Requires-Dist: halo
Requires-Dist: tqdm
Requires-Dist: func-timeout
Dynamic: author
Dynamic: home-page
Dynamic: license
Dynamic: license-file
Dynamic: project-url
Dynamic: requires-dist
Dynamic: requires-python
Dynamic: summary
